dukaonesdk/__init__.py
dukaonesdk/device.py
dukaonesdk/dukaclient.py
dukaonesdk/dukapacket.py
dukaonesdk/mode.py
dukaonesdk/responsepacket.py
dukaonesdk/speed.py
dukaonesdk-1.0.5.dist-info/licenses/license.txt
dukaonesdk-1.0.5.dist-info/METADATA
dukaonesdk-1.0.5.dist-info/WHEEL
dukaonesdk-1.0.5.dist-info/top_level.txt
dukaonesdk-1.0.5.dist-info/RECORD
